pt_lemmatizer/__init__.py
pt_lemmatizer/pt_lemmatizer.py
pt_lemmatizer/data/lemmatization-pt.txt
pt_lemmatizer-2.1.18.dist-info/LICENSE
pt_lemmatizer-2.1.18.dist-info/METADATA
pt_lemmatizer-2.1.18.dist-info/WHEEL
pt_lemmatizer-2.1.18.dist-info/top_level.txt
pt_lemmatizer-2.1.18.dist-info/RECORD
