Metadata-Version: 2.1
Name: pt-lemmatizer
Version: 2.1.18
Summary: A NLP package for Portuguese Lemmatization.
Home-page: UNKNOWN
Author: Naomi Lago
Author-email: <info@naomilago.com>
License: UNKNOWN
Keywords: python,portuguese,lemmatizer,nlp
Platform: UNKNOWN
Classifier: Development Status :: 5 - Production/Stable
Classifier: Intended Audience :: Developers
Classifier: Programming Language :: Python :: 3
Classifier: License :: OSI Approved :: MIT License
Classifier: Operating System :: OS Independent
License-File: LICENSE
Requires-Dist: unidecode
